optseq/__init__.py
optseq/optseq-linux
optseq/optseq-mac
optseq/optseq.exe
optseq/optseq.py
optseq/py.typed
optseq-0.1.6.dist-info/METADATA
optseq-0.1.6.dist-info/WHEEL
optseq-0.1.6.dist-info/licenses/LICENSE
optseq-0.1.6.dist-info/RECORD
