Metadata-Version: 2.4
Name: optseq
Version: 0.1.6
Summary: OptSeq is a general-purpose scheduling optimization solver specialized for scheduling optimization.
Author-email: Mikio Kubo <kubo@kaiyodai.ac.jp>, Saito Tsutomu <tsutomu7@hotmail.co.jp>
License-File: LICENSE
Requires-Python: >=3.10
Requires-Dist: pydantic>=2.10.5
Provides-Extra: all
Requires-Dist: pandas; extra == 'all'
Requires-Dist: plotly; extra == 'all'
